rpgtk/__init__.py
rpgtk/cards/__init__.py
rpgtk/cards/constants.py
rpgtk/cards/deck.py
rpgtk/core.py
rpgtk/exceptions.py
rpgtk/items/__init__.py
rpgtk/items/base.py
rpgtk/items/item.py
rpgtk-0.4.1.dist-info/LICENSE
rpgtk-0.4.1.dist-info/WHEEL
rpgtk-0.4.1.dist-info/METADATA
rpgtk-0.4.1.dist-info/RECORD
