Metadata-Version: 2.1
Name: rpgtk
Version: 0.4.1
Summary: the python rpg toolkit
Home-page: https://github.com/is-gabs/rpgtk
License: MIT
Author: Gabriel Sarmento
Author-email: gabrielfs.bot@gmail.com
Requires-Python: >=3.9,<4.0
Classifier: Intended Audience :: Developers
Classifier: License :: OSI Approved :: MIT License
Classifier: Operating System :: OS Independent
Classifier: Programming Language :: Python :: 3
Classifier: Programming Language :: Python :: 3.9
Classifier: Programming Language :: Python :: 3.10
Classifier: Programming Language :: Python :: 3
Project-URL: Repository, https://github.com/is-gabs/rpgtk
